acelyzer/acelyzer.py
aiu_trace_analyzer/__init__.py
aiu_trace_analyzer/constants.py
aiu_trace_analyzer/logger.py
aiu_trace_analyzer/trace_view.py
aiu_trace_analyzer/types.py
aiu_trace_analyzer/core/acelyzer.py
aiu_trace_analyzer/core/duplicate_hold.py
aiu_trace_analyzer/core/engine.py
aiu_trace_analyzer/core/processing.py
aiu_trace_analyzer/core/stage_profile.py
aiu_trace_analyzer/export/exporter.py
aiu_trace_analyzer/ingest/ingestion.py
aiu_trace_analyzer/pipeline/__init__.py
aiu_trace_analyzer/pipeline/barrier.py
aiu_trace_analyzer/pipeline/be_pair.py
aiu_trace_analyzer/pipeline/cmpt_collection.py
aiu_trace_analyzer/pipeline/coll_group.py
aiu_trace_analyzer/pipeline/context.py
aiu_trace_analyzer/pipeline/correctness.py
aiu_trace_analyzer/pipeline/dma.py
aiu_trace_analyzer/pipeline/drop_global_event.py
aiu_trace_analyzer/pipeline/filter.py
aiu_trace_analyzer/pipeline/flex_job_offset.py
aiu_trace_analyzer/pipeline/hashqueue.py
aiu_trace_analyzer/pipeline/inverse_ts.py
aiu_trace_analyzer/pipeline/iteration_detect.py
aiu_trace_analyzer/pipeline/make_slice.py
aiu_trace_analyzer/pipeline/mappings.py
aiu_trace_analyzer/pipeline/mp_calc_bw.py
aiu_trace_analyzer/pipeline/mp_calc_bw_v2.py
aiu_trace_analyzer/pipeline/mp_sync.py
aiu_trace_analyzer/pipeline/mp_sync_tight.py
aiu_trace_analyzer/pipeline/mp_sync_v2.py
aiu_trace_analyzer/pipeline/normalize.py
aiu_trace_analyzer/pipeline/overlap.py
aiu_trace_analyzer/pipeline/power.py
aiu_trace_analyzer/pipeline/rcu_utilization.py
aiu_trace_analyzer/pipeline/sort.py
aiu_trace_analyzer/pipeline/stats.py
aiu_trace_analyzer/pipeline/stats_v2.py
aiu_trace_analyzer/pipeline/tb_refinement.py
aiu_trace_analyzer/pipeline/template.py
aiu_trace_analyzer/pipeline/tid_mapping.py
aiu_trace_analyzer/pipeline/time_align.py
aiu_trace_analyzer/pipeline/timesync.py
aiu_trace_analyzer/pipeline/tools.py
aiu_trace_analyzer/pipeline/tripple_event.py
aiu_trace_analyzer/profiles/default.json
aiu_trace_analyzer/profiles/everything.json
aiu_trace_analyzer-1.0.0.dist-info/licenses/LICENSE
aiu_trace_analyzer-1.0.0.dist-info/METADATA
aiu_trace_analyzer-1.0.0.dist-info/WHEEL
aiu_trace_analyzer-1.0.0.dist-info/entry_points.txt
aiu_trace_analyzer-1.0.0.dist-info/top_level.txt
aiu_trace_analyzer-1.0.0.dist-info/RECORD
