Metadata-Version: 2.4
Name: aiu_trace_analyzer
Version: 1.0.0
Summary: Event Profile/Trace Analyzer (acelyzer) for post-processing, combining, or enhancing of trace files.
Author: Lars Schneidenbach et. al
License-Expression: Apache-2.0
Project-URL: Homepage, https://github.com/IBM/aiu-trace-analyzer
Project-URL: Issues, https://github.com/IBM/aiu-trace-analyzer/issues
Classifier: Programming Language :: Python :: 3 :: Only
Classifier: Operating System :: POSIX
Classifier: Topic :: Scientific/Engineering :: Artificial Intelligence
Requires-Python: >=3.9
License-File: LICENSE
Requires-Dist: numpy
Requires-Dist: pandas
Provides-Extra: test
Requires-Dist: pytest; extra == "test"
Dynamic: license-file
